Workbook

Sheet Active subscribers
A1: customer | B1: lat | C1: lon | D1: address | E1: city | F1: state | G1: zip | H1: download | I1: upload | J1: voip_lines_quantity | K1: business_customer | L1: technology
A2: 1668921 | B2: =VLOOKUP(A2,'Subscribers Address'!A:G,6, FALSE) -> 40.36134 | C2: =VLOOKUP(A2,'Subscribers Address'!A:G,7, FALSE) -> -78.727006 | D2: 1735 Frankstown Rd | E2: Summermill | F2: PA | G2: 15958 | H2: 13 | I2: 8 | J2: 0 | K2: 0 | L2: wireless_unlicensed
A3: 1668873 | B3: =VLOOKUP(A3,'Subscribers Address'!A:G,6, FALSE) -> 40.440965 | C3: =VLOOKUP(A3,'Subscribers Address'!A:G,7, FALSE) -> -79.097709 | D3: 230 Rumble Road | E3: New Florence | F3: PA | G3: 15944 | H3: 45 | I3: 20 | J3: 0 | K3: 0 | L3: wireless_unlicensed
A4: 1669484 | B4: =VLOOKUP(A4,'Subscribers Address'!A:G,6, FALSE) -> 40.479001 | C4: =VLOOKUP(A4,'Subscribers Address'!A:G,7, FALSE) -> -79.215064 | D4: 1371 McConnell Rd | E4: Blairsville | F4: PA | G4: 15717 | H4: 57 | I4: 20 | J4: 0 | K4: 0 | L4: wireless_unlicensed
A5: 1669855 | B5: =VLOOKUP(A5,'Subscribers Address'!A:G,6, FALSE) -> 40.59571 | C5: =VLOOKUP(A5,'Subscribers Address'!A:G,7, FALSE) -> -78.569771 | D5: 1199 Schoolhouse Drive | E5: Dysart | F5: PA | G5: 16636 | H5: 110 | I5: 25 | J5: 0 | K5: 0 | L5: wireless_unlicensed
A6: 2452198 | B6: =VLOOKUP(A6,'Subscribers Address'!A:G,6, FALSE) -> 40.527242 | C6: =VLOOKUP(A6,'Subscribers Address'!A:G,7, FALSE) -> -78.404417 | D6: 401 22nd Avenue | E6: Altoona | F6: PA | G6: 16601 | H6: 50 | I6: 20 | J6: 0 | K6: 0 | L6: wireless_unlicensed
A7: 1668784 | B7: =VLOOKUP(A7,'Subscribers Address'!A:G,6, FALSE) -> 40.495677 | C7: =VLOOKUP(A7,'Subscribers Address'!A:G,7, FALSE) -> -78.736104 | D7: 116 Colver Rd | E7: Ebensburg | F7: PA | G7: 15931 | H7: 57 | I7: 20 | J7: 0 | K7: 0 | L7: wireless_unlicensed
A8: 2166138 | B8: =VLOOKUP(A8,'Subscribers Address'!A:G,6, FALSE) -> 40.529485 | C8: =VLOOKUP(A8,'Subscribers Address'!A:G,7, FALSE) -> -78.665161 | D8: 772 Stock Road | E8: Loretto | F8: PA | G8: 15940 | H8: 13 | I8: 8 | J8: 0 | K8: 0 | L8: wireless_unlicensed
A9: 1669154 | B9: =VLOOKUP(A9,'Subscribers Address'!A:G,6, FALSE) -> 40.137739 | C9: =VLOOKUP(A9,'Subscribers Address'!A:G,7, FALSE) -> -78.835721 | D9: 330 Miller Run Road | E9: Hooversville | F9: PA | G9: 15936 | H9: 13 | I9: 8 | J9: 0 | K9: 0 | L9: wireless_unlicensed
A10: 1668851 | B10: =VLOOKUP(A10,'Subscribers Address'!A:G,6, FALSE) -> 40.877792 | C10: =VLOOKUP(A10,'Subscribers Address'!A:G,7, FALSE) -> -78.34393 | D10: 760 Red Schoolhouse Road | E10: Osceola Mills | F10: PA | G10: 16666 | H10: 13 | I10: 8 | J10: 0 | K10: 0 | L10: wireless_unlicensed
A11: 1669413 | B11: =VLOOKUP(A11,'Subscribers Address'!A:G,6, FALSE) -> 40.620092 | C11: =VLOOKUP(A11,'Subscribers Address'!A:G,7, FALSE) -> -78.563011 | D11: 1176 St Augustine Rd | E11: Patton | F11: PA | G11: 16668 | H11: 30 | I11: 15 | J11: 1 | K11: 0 | L11: wireless_unlicensed
A12: 1670470 | B12: =VLOOKUP(A12,'Subscribers Address'!A:G,6, FALSE) -> 40.530643 | C12: =VLOOKUP(A12,'Subscribers Address'!A:G,7, FALSE) -> -78.619377 | D12: 371 Sharpe Rd | E12: Loretto | F12: PA | G12: 15940 | H12: 110 | I12: 110 | J12: 0 | K12: 0 | L12: Fiber
A13: 1875566 | B13: =VLOOKUP(A13,'Subscribers Address'!A:G,6, FALSE) -> 40.649737 | C13: =VLOOKUP(A13,'Subscribers Address'!A:G,7, FALSE) -> -78.80476 | D13: 426 Farrell Road | E13: Marsteller | F13: PA | G13: 15760 | H13: 30 | I13: 15 | J13: 0 | K13: 0 | L13: wireless_unlicensed
... A90: 1670450 | B90: =VLOOKUP(A90,'Subscribers Address'!A:G,6, FALSE) -> 40.496273 | C90: =VLOOKUP(A90,'Subscribers Address'!A:G,7, FALSE) -> -78.765963 | D90: 120 Sanborn Lane | E90: Ebensburg | F90: PA | G90: 15931 | H90: 600 | I90: 600 | J90: 0 | K90: 1 | L90: wireless_unlicensed
A91: 1768186 | B91: 40.46051 | C91: -78.76031 | D91: 388 Industrial Park Road | E91: Ebensburg | F91: PA | G91: 15931 | H91: 57 | I91: 20 | J91: 0 | K91: 0 | L91: wireless_unlicensed
A92: 1768131 | B92: =VLOOKUP(A92,'Subscribers Address'!A:G,6, FALSE) -> 40.431706 | C92: =VLOOKUP(A92,'Subscribers Address'!A:G,7, FALSE) -> -78.746627 | D92: 259 Charlies Road | E92: Summerhill | F92: PA | G92: 15958 | H92: 57 | I92: 20 | J92: 1 | K92: 0 | L92: wireless_unlicensed
A93: 2029903 | B93: =VLOOKUP(A93,'Subscribers Address'!A:G,6, FALSE) -> 40.020027 | C93: =VLOOKUP(A93,'Subscribers Address'!A:G,7, FALSE) -> -78.954831 | D93: 110 Petersburg Drive | E93: Friedens | F93: PA | G93: 15541 | H93: 30 | I93: 15 | J93: 0 | K93: 0 | L93: wireless_unlicensed
A94: 2220197 | B94: =VLOOKUP(A94,'Subscribers Address'!A:G,6, FALSE) -> 40.527381 | C94: =VLOOKUP(A94,'Subscribers Address'!A:G,7, FALSE) -> -78.601765 | D94: 706 Lincoln Road | E94: Loretto | F94: PA | G94: 15940 | H94: 110 | I94: 110 | J94: 0 | K94: 0 | L94: Fiber
A95: 1773644 | B95: =VLOOKUP(A95,'Subscribers Address'!A:G,6, FALSE) -> 40.604135 | C95: =VLOOKUP(A95,'Subscribers Address'!A:G,7, FALSE) -> -78.784182 | D95: 643 Ridge Rd | E95: Nicktown | F95: PA | G95: 15762 | H95: 45 | I95: 20 | J95: 0 | K95: 0 | L95: wireless_unlicensed
A96: 1670103 | B96: =VLOOKUP(A96,'Subscribers Address'!A:G,6, FALSE) -> 40.60411 | C96: =VLOOKUP(A96,'Subscribers Address'!A:G,7, FALSE) -> -78.834746 | D96: 184 Log Road | E96: Nicktown | F96: PA | G96: 15762 | H96: 57 | I96: 20 | J96: 0 | K96: 0 | L96: wireless_unlicensed
A97: 1898662 | B97: =VLOOKUP(A97,'Subscribers Address'!A:G,6, FALSE) -> 40.500635 | C97: =VLOOKUP(A97,'Subscribers Address'!A:G,7, FALSE) -> -78.59572 | D97: 676 Iceplant Road | E97: Gallitzin | F97: PA | G97: 16641 | H97: 45 | I97: 20 | J97: 0 | K97: 0 | L97: wireless_unlicensed
A98: 1678860 | B98: =VLOOKUP(A98,'Subscribers Address'!A:G,6, FALSE) -> 40.394389 | C98: =VLOOKUP(A98,'Subscribers Address'!A:G,7, FALSE) -> -78.770285 | D98: 252 Knipple Rd | E98: Mineral Point | F98: PA | G98: 15942 | H98: 13 | I98: 8 | J98: 0 | K98: 0 | L98: wireless_unlicensed
A99: 1871651 | B99: =VLOOKUP(A99,'Subscribers Address'!A:G,6, FALSE) -> 40.705764 | C99: =VLOOKUP(A99,'Subscribers Address'!A:G,7, FALSE) -> -78.724171 | D99: 787 Carpinello Road | E99: Hastings | F99: PA | G99: 16646 | H99: 30 | I99: 15 | J99: 0 | K99: 0 | L99: wireless_unlicensed
A100: 1668626 | B100: =VLOOKUP(A100,'Subscribers Address'!A:G,6, FALSE) -> 40.574827 | C100: =VLOOKUP(A100,'Subscribers Address'!A:G,7, FALSE) -> -78.790515 | D100: 2251 Lute Rd | E100: Ebensburg | F100: PA | G100: 15931 | H100: 45 | I100: 20 | J100: 0 | K100: 0 | L100: wireless_unlicensed
A101: 1668664 | B101: =VLOOKUP(A101,'Subscribers Address'!A:G,6, FALSE) -> 40.356046 | C101: =VLOOKUP(A101,'Subscribers Address'!A:G,7, FALSE) -> -78.747531 | D101: 650 Betz Rd | E101: Sidman | F101: PA | G101: 15955 | H101: 30 | I101: 15 | J101: 0 | K101: 0 | L101: wireless_unlicensed
A102: 2031259 | B102: =VLOOKUP(A102,'Subscribers Address'!A:G,6, FALSE) -> 40.695802 | C102: =VLOOKUP(A102,'Subscribers Address'!A:G,7, FALSE) -> -78.616194 | D102: 2189 Saint Lawrence Road | E102: Patton | F102: PA | G102: 16668 | H102: 57 | I102: 20 | J102: 0 | K102: 0 | L102: wireless_unlicensed
A103: 1669566 | B103: =VLOOKUP(A103,'Subscribers Address'!A:G,6, FALSE) -> 40.62091 | C103: =VLOOKUP(A103,'Subscribers Address'!A:G,7, FALSE) -> -75.448174 | D103: 813 North Fenwick Street | E103: Allentown | F103: PA | G103: 18109 | H103: 10 | I103: 25 | J103: 0 | K103: 0 | L103: wireless_unlicensed
... A107: 1669996 | B107: =VLOOKUP(A107,'Subscribers Address'!A:G,6, FALSE) -> 40.62722 | C107: =VLOOKUP(A107,'Subscribers Address'!A:G,7, FALSE) -> -78.555298 | D107: 1446 St Augustine Road | E107: Dysart | F107: PA | G107: 16636 | H107: 13 | I107: 8 | J107: 0 | K107: 0 | L107: wireless_unlicensed
A108: 1668848 | B108: 40.507105 | C108: -78.40755 | D108: 2035 Broad Ave | E108: Altoona | F108: PA | G108: 16601 | H108: 13 | I108: 8 | J108: 0 | K108: 0 | L108: wireless_unlicensed
A109: 1668849 | B109: 40.482915 | C109: -78.399747 | D109: 3515 Pleasant Valley Blvd | E109: Altoona | F109: PA | G109: 16602 | H109: 57 | I109: 20 | J109: 0 | K109: 0 | L109: wireless_unlicensed
A110: 2344721 | B110: =VLOOKUP(A110,'Subscribers Address'!A:G,6, FALSE) -> 40.610519 | C110: =VLOOKUP(A110,'Subscribers Address'!A:G,7, FALSE) -> -78.667109 | D110: 855 Sr4015 | E110: Patton | F110: PA | G110: 16668 | H110: 57 | I110: 20 | J110: 0 | K110: 0 | L110: wireless_unlicensed
A111: 1668618 | B111: =VLOOKUP(A111,'Subscribers Address'!A:G,6, FALSE) -> 40.410865 | C111: =VLOOKUP(A111,'Subscribers Address'!A:G,7, FALSE) -> -78.769336 | D111: 361 Tower Road | E111: Summerhill | F111: PA | G111: 15958 | H111: 13 | I111: 8 | J111: 0 | K111: 0 | L111: wireless_unlicensed
A112: 1668975 | B112: =VLOOKUP(A112,'Subscribers Address'!A:G,6, FALSE) -> 40.406683 | C112: =VLOOKUP(A112,'Subscribers Address'!A:G,7, FALSE) -> -78.908991 | D112: 255 WEEPING WILLOW LN | E112: JOHNSTOWN | F112: PA | G112: 15906 | H112: 13 | I112: 8 | J112: 0 | K112: 0 | L112: wireless_unlicensed
A113: 1669040 | B113: =VLOOKUP(A113,'Subscribers Address'!A:G,6, FALSE) -> 40.590372 | C113: =VLOOKUP(A113,'Subscribers Address'!A:G,7, FALSE) -> -78.673864 | D113: 653 Feighner Rd | E113: Carrolltown | F113: PA | G113: 15722 | H113: 110 | I113: 110 | J113: 0 | K113: 0 | L113: Fiber
A114: 1670028 | B114: =VLOOKUP(A114,'Subscribers Address'!A:G,6, FALSE) -> 40.137734 | C114: =VLOOKUP(A114,'Subscribers Address'!A:G,7, FALSE) -> -78.856821 | D114: 344 School Road | E114: Hooversville | F114: PA | G114: 15936 | H114: 30 | I114: 15 | J114: 0 | K114: 0 | L114: wireless_unlicensed
A115: 1670191 | B115: =VLOOKUP(A115,'Subscribers Address'!A:G,6, FALSE) -> 40.63249 | C115: =VLOOKUP(A115,'Subscribers Address'!A:G,7, FALSE) -> -78.603129 | D115: 104 Warefield Ln | E115: Patton | F115: PA | G115: 16668 | H115: 30 | I115: 15 | J115: 0 | K115: 0 | L115: wireless_unlicensed
A116: 1670300 | B116: =VLOOKUP(A116,'Subscribers Address'!A:G,6, FALSE) -> 40.583591 | C116: =VLOOKUP(A116,'Subscribers Address'!A:G,7, FALSE) -> -78.75954 | D116: 174 Zeke Ln | E116: Carrolltown | F116: PA | G116: 15722 | H116: 13 | I116: 8 | J116: 0 | K116: 0 | L116: wireless_unlicensed
A117: 1689885 | B117: =VLOOKUP(A117,'Subscribers Address'!A:G,6, FALSE) -> 40.165256 | C117: =VLOOKUP(A117,'Subscribers Address'!A:G,7, FALSE) -> -78.869004 | D117: 1961 Ridge Road | E117: Hooversville | F117: PA | G117: 15936 | H117: 13 | I117: 8 | J117: 0 | K117: 0 | L117: wireless_unlicensed
A118: 1765680 | B118: =VLOOKUP(A118,'Subscribers Address'!A:G,6, FALSE) -> 40.467896 | C118: =VLOOKUP(A118,'Subscribers Address'!A:G,7, FALSE) -> -78.631651 | D118: 151 Criste Road | E118: Loretto | F118: PA | G118: 15940 | H118: 13 | I118: 8 | J118: 0 | K118: 0 | L118: wireless_unlicensed
A119: 1832076 | B119: =VLOOKUP(A119,'Subscribers Address'!A:G,6, FALSE) -> 40.491365 | C119: =VLOOKUP(A119,'Subscribers Address'!A:G,7, FALSE) -> -78.96168 | D119: 2854 Barkley Church Rd | E119: Vintondale | F119: PA | G119: 15961 | H119: 30 | I119: 15 | J119: 0 | K119: 0 | L119: wireless_unlicensed
A120: 2535626 | B120: =VLOOKUP(A120,'Subscribers Address'!A:G,6, FALSE) -> 40.42322 | C120: =VLOOKUP(A120,'Subscribers Address'!A:G,7, FALSE) -> -78.59508 | D120: 516 Memorial Drive | E120: Lilly | F120: PA | G120: 15938 | H120: 13 | I120: 8 | J120: 0 | K120: 0 | L120: wireless_unlicensed
A121: 2347080 | B121: =VLOOKUP(A121,'Subscribers Address'!A:G,6, FALSE) -> 40.508156 | C121: =VLOOKUP(A121,'Subscribers Address'!A:G,7, FALSE) -> -78.591642 | D121: 1255 Syberton Road | E121: Gallitzin | F121: PA | G121: 16641 | H121: 110 | I121: 110 | J121: 1 | K121: 0 | L121: Fiber
... A508: 2495066 | B508: =VLOOKUP(A508,'Subscribers Address'!A:G,6, FALSE) -> 40.677677 | C508: =VLOOKUP(A508,'Subscribers Address'!A:G,7, FALSE) -> -78.685024 | D508: 602 Pine Road | E508: Hastings | F508: PA | G508: 16646 | H508: 13 | I508: 8 | J508: 0 | K508: 0 | L508: wireless_unlicensed
A509: 2508831 | B509: 40.134844 | C509: -78.945815 | D509: 236 Rustic Road | E509: Hooversville | F509: PA | G509: 15936 | H509: 30 | I509: 15 | J509: 0 | K509: 0 | L509: wireless_unlicensed
A510: 2514700 | B510: =VLOOKUP(A510,'Subscribers Address'!A:G,6, FALSE) -> 41.955943 | C510: =VLOOKUP(A510,'Subscribers Address'!A:G,7, FALSE) -> -78.655646 | D510: 4 South Center Street | E510: Corry | F510: PA | G510: 16407 | H510: 210 | I510: 80 | J510: 0 | K510: 0 | L510: wireless_unlicensed
A511: 2200579 | B511: =VLOOKUP(A511,'Subscribers Address'!A:G,6, FALSE) -> 41.383924 | C511: =VLOOKUP(A511,'Subscribers Address'!A:G,7, FALSE) -> -81.222051 | D511: 11569 U.S. 422 | E511: Penn Run | F511: PA | G511: 15765 | H511: 30 | I511: 15 | J511: 0 | K511: 0 | L511: wireless_unlicensed
A512: 1669646 | B512: =VLOOKUP(A512,'Subscribers Address'!A:G,6, FALSE) -> 40.655952 | C512: =VLOOKUP(A512,'Subscribers Address'!A:G,7, FALSE) -> -78.515013 | D512: 1800 Marina Road | E512: Fallentimber,Pa 16639 | F512: PA | G512: 16639 | H512: 30 | I512: 15 | J512: 0 | K512: 0 | L512: wireless_unlicensed
A513: 2453868 | B513: =VLOOKUP(A513,'Subscribers Address'!A:G,6, FALSE) -> 40.437322 | C513: =VLOOKUP(A513,'Subscribers Address'!A:G,7, FALSE) -> -78.666742 | D513: 1545 Munster Road | E513: Portage | F513: PA | G513: 15946 | H513: 30 | I513: 15 | J513: 0 | K513: 0 | L513: wireless_unlicensed
A514: 1669568 | B514: =VLOOKUP(A514,'Subscribers Address'!A:G,6, FALSE) -> 40.649735 | C514: =VLOOKUP(A514,'Subscribers Address'!A:G,7, FALSE) -> -78.806506 | D514: 403 Farrell Road | E514: Marsteller | F514: PA | G514: 15760 | H514: 57 | I514: 20 | J514: 0 | K514: 0 | L514: wireless_unlicensed
A515: 1669581 | B515: =VLOOKUP(A515,'Subscribers Address'!A:G,6, FALSE) -> 40.433894 | C515: =VLOOKUP(A515,'Subscribers Address'!A:G,7, FALSE) -> -78.700276 | D515: 115 Howells Hill Rd | E515: Portage | F515: PA | G515: 15946 | H515: 110 | I515: 110 | J515: 0 | K515: 0 | L515: Fiber
A516: 1669739 | B516: =VLOOKUP(A516,'Subscribers Address'!A:G,6, FALSE) -> 40.361186 | C516: =VLOOKUP(A516,'Subscribers Address'!A:G,7, FALSE) -> -78.720131 | D516: 1896 Fieldstone Ave | E516: Summerhill | F516: PA | G516: 15958 | H516: 30 | I516: 15 | J516: 0 | K516: 0 | L516: wireless_unlicensed
A517: 1670315 | B517: =VLOOKUP(A517,'Subscribers Address'!A:G,6, FALSE) -> 40.508555 | C517: =VLOOKUP(A517,'Subscribers Address'!A:G,7, FALSE) -> -79.216525 | D517: 1860 Coal road | E517: Blairsville | F517: PA | G517: 15717 | H517: 13 | I517: 8 | J517: 0 | K517: 0 | L517: wireless_unlicensed
A518: 1787266 | B518: =VLOOKUP(A518,'Subscribers Address'!A:G,6, FALSE) -> 40.505676 | C518: =VLOOKUP(A518,'Subscribers Address'!A:G,7, FALSE) -> -78.58545 | D518: 368 Stevens Road | E518: Gallitzin | F518: PA | G518: 16641 | H518: 30 | I518: 15 | J518: 0 | K518: 0 | L518: wireless_gaa
A519: 2223311 | B519: =VLOOKUP(A519,'Subscribers Address'!A:G,6, FALSE) -> 40.498556 | C519: =VLOOKUP(A519,'Subscribers Address'!A:G,7, FALSE) -> -78.653464 | D519: 523 Thomas Road | E519: Loretto | F519: PA | G519: 15940 | H519: 1000 | I519: 1000 | J519: 0 | K519: 0 | L519: Fiber
A520: 1668675 | B520: =VLOOKUP(A520,'Subscribers Address'!A:G,6, FALSE) -> 40.567822 | C520: =VLOOKUP(A520,'Subscribers Address'!A:G,7, FALSE) -> -78.452126 | D520: 2498 Whopsy Rd | E520: Dysart | F520: PA | G520: 16636 | H520: 13 | I520: 8 | J520: 0 | K520: 0 | L520: wireless_unlicensed
A521: 1669109 | B521: =VLOOKUP(A521,'Subscribers Address'!A:G,6, FALSE) -> 40.570078 | C521: =VLOOKUP(A521,'Subscribers Address'!A:G,7, FALSE) -> -78.737217 | D521: 2358 Colver Road | E521: Ebensburg | F521: PA | G521: 15931 | H521: 53 | I521: 20 | J521: 0 | K521: 0 | L521: wireless_unlicensed
... A638: 1668843 | B638: =VLOOKUP(A638,'Subscribers Address'!A:G,6, FALSE) -> 40.592391 | C638: =VLOOKUP(A638,'Subscribers Address'!A:G,7, FALSE) -> -78.853891 | D638: 2375 Killen School Rd | E638: Nicktown | F638: PA | G638: 15762 | H638: 45 | I638: 20 | J638: 1 | K638: 0 | L638: wireless_unlicensed
A639: 1874111 | B639: 40.628946 | C639: -78.556758 | D639: 521 Nagle Road | E639: Patton | F639: PA | G639: 16668 | H639: 30 | I639: 15 | J639: 0 | K639: 0 | L639: wireless_unlicensed
A640: 1878458 | B640: =VLOOKUP(A640,'Subscribers Address'!A:G,6, FALSE) -> 40.564198 | C640: =VLOOKUP(A640,'Subscribers Address'!A:G,7, FALSE) -> -78.807507 | D640: 417 Wolfe Road | E640: Ebensburg | F640: PA | G640: 15931 | H640: 30 | I640: 15 | J640: 0 | K640: 0 | L640: wireless_unlicensed
A641: 2049135 | B641: =VLOOKUP(A641,'Subscribers Address'!A:G,6, FALSE) -> 40.37813 | C641: =VLOOKUP(A641,'Subscribers Address'!A:G,7, FALSE) -> -78.760576 | D641: 112 Indian Bowl Ln | E641: Summerhill | F641: PA | G641: 15958 | H641: 45 | I641: 20 | J641: 0 | K641: 0 | L641: wireless_unlicensed
A642: 2214784 | B642: =VLOOKUP(A642,'Subscribers Address'!A:G,6, FALSE) -> 40.461215 | C642: =VLOOKUP(A642,'Subscribers Address'!A:G,7, FALSE) -> -78.961901 | D642: 2163 River Road | E642: Vintondale | F642: PA | G642: 15961 | H642: 30 | I642: 15 | J642: 0 | K642: 0 | L642: wireless_unlicensed
A643: 1875549 | B643: =VLOOKUP(A643,'Subscribers Address'!A:G,6, FALSE) -> 40.654349 | C643: =VLOOKUP(A643,'Subscribers Address'!A:G,7, FALSE) -> -78.588865 | D643: 1166 Grozanick Road | E643: Patton | F643: PA | G643: 16668 | H643: 45 | I643: 20 | J643: 0 | K643: 0 | L643: wireless_unlicensed
A644: 1831492 | B644: =VLOOKUP(A644,'Subscribers Address'!A:G,6, FALSE) -> 40.612636 | C644: =VLOOKUP(A644,'Subscribers Address'!A:G,7, FALSE) -> -78.868967 | D644: 87 Kinter Station Road | E644: Northern Cambria | F644: PA | G644: 15714 | H644: 30 | I644: 15 | J644: 0 | K644: 0 | L644: wireless_unlicensed
A645: 1669023 | B645: =VLOOKUP(A645,'Subscribers Address'!A:G,6, FALSE) -> 40.398985 | C645: =VLOOKUP(A645,'Subscribers Address'!A:G,7, FALSE) -> -78.796538 | D645: 1307 Swigle Mountain Road | E645: Mineral Point | F645: PA | G645: 15942 | H645: 30 | I645: 15 | J645: 0 | K645: 0 | L645: wireless_unlicensed
A646: 1669134 | B646: =VLOOKUP(A646,'Subscribers Address'!A:G,6, FALSE) -> 40.575891 | C646: =VLOOKUP(A646,'Subscribers Address'!A:G,7, FALSE) -> -78.594467 | D646: 2733 Colonel Drake Highway | E646: Ashville | F646: PA | G646: 16613 | H646: 110 | I646: 110 | J646: 0 | K646: 0 | L646: Fiber
A647: 1829639 | B647: =VLOOKUP(A647,'Subscribers Address'!A:G,6, FALSE) -> 40.449034 | C647: =VLOOKUP(A647,'Subscribers Address'!A:G,7, FALSE) -> -79.239994 | D647: 110 Country Ln Rd | E647: Blairsville | F647: PA | G647: 15717 | H647: 13 | I647: 8 | J647: 0 | K647: 0 | L647: wireless_unlicensed
A648: 2281810 | B648: =VLOOKUP(A648,'Subscribers Address'!A:G,6, FALSE) -> 40.841621 | C648: =VLOOKUP(A648,'Subscribers Address'!A:G,7, FALSE) -> -78.844229 | D648: 216 Spencer Hollow Drive | E648: Glen Campbell | F648: PA | G648: 15742 | H648: 30 | I648: 15 | J648: 0 | K648: 0 | L648: wireless_unlicensed
A649: 1669209 | B649: =VLOOKUP(A649,'Subscribers Address'!A:G,6, FALSE) -> 40.437278 | C649: =VLOOKUP(A649,'Subscribers Address'!A:G,7, FALSE) -> -79.154512 | D649: 104 Dusty Lane | E649: Blairsville | F649: PA | G649: 15717 | H649: 100 | I649: 25 | J649: 0 | K649: 0 | L649: wireless_unlicensed
A650: 2323092 | B650: =VLOOKUP(A650,'Subscribers Address'!A:G,6, FALSE) -> 40.482523 | C650: =VLOOKUP(A650,'Subscribers Address'!A:G,7, FALSE) -> -78.734757 | D650: 937 West High Street | E650: Ebensburg | F650: PA | G650: 15931 | H650: 110 | I650: 110 | J650: 1 | K650: 0 | L650: wireless_unlicensed
A651: 1866004 | B651: =VLOOKUP(A651,'Subscribers Address'!A:G,6, FALSE) -> 40.697413 | C651: =VLOOKUP(A651,'Subscribers Address'!A:G,7, FALSE) -> -78.626242 | D651: 1958 St Lawrence Rd | E651: Patton | F651: PA | G651: 16668 | H651: 30 | I651: 15 | J651: 0 | K651: 0 | L651: wireless_unlicensed
... A865: 1669660 | B865: =VLOOKUP(A865,'Subscribers Address'!A:G,6, FALSE) -> 40.397482 | C865: =VLOOKUP(A865,'Subscribers Address'!A:G,7, FALSE) -> -78.888393 | D865: 2173 Benshoff Hill Rd | E865: Johnstown | F865: PA | G865: 15909 | H865: 13 | I865: 8 | J865: 0 | K865: 0 | L865: wireless_unlicensed
A866: 1669679 | B866: 40.451583 | C866: -78.987312 | D866: 307 Virginia Heights Lane | E866: Seward | F866: PA | G866: 15954 | H866: 30 | I866: 12 | J866: 0 | K866: 0 | L866: wireless_unlicensed
A867: 1669982 | B867: =VLOOKUP(A867,'Subscribers Address'!A:G,6, FALSE) -> 40.419867 | C867: =VLOOKUP(A867,'Subscribers Address'!A:G,7, FALSE) -> -78.772502 | D867: 549 Benshoff Road | E867: Summerhill | F867: PA | G867: 15958 | H867: 13 | I867: 8 | J867: 0 | K867: 0 | L867: wireless_unlicensed
A868: 1670066 | B868: =VLOOKUP(A868,'Subscribers Address'!A:G,6, FALSE) -> 40.894733 | C868: =VLOOKUP(A868,'Subscribers Address'!A:G,7, FALSE) -> -73.942554 | D868: 544 Cunningham Road | E868: Ebensburg | F868: PA | G868: 15931 | H868: 45 | I868: 20 | J868: 0 | K868: 0 | L868: wireless_unlicensed
A869: 1670296 | B869: =VLOOKUP(A869,'Subscribers Address'!A:G,6, FALSE) -> 40.560068 | C869: =VLOOKUP(A869,'Subscribers Address'!A:G,7, FALSE) -> -78.548629 | D869: 223 ST William Lane | E869: Ashville | F869: PA | G869: 16613 | H869: 13 | I869: 8 | J869: 0 | K869: 0 | L869: wireless_unlicensed
A870: 1670320 | B870: =VLOOKUP(A870,'Subscribers Address'!A:G,6, FALSE) -> 40.593291 | C870: =VLOOKUP(A870,'Subscribers Address'!A:G,7, FALSE) -> -78.481626 | D870: 794 Richland Rd | E870: Dysart | F870: PA | G870: 16636 | H870: 13 | I870: 8 | J870: 0 | K870: 0 | L870: wireless_unlicensed
A871: 1670357 | B871: =VLOOKUP(A871,'Subscribers Address'!A:G,6, FALSE) -> 40.577926 | C871: =VLOOKUP(A871,'Subscribers Address'!A:G,7, FALSE) -> -78.610414 | D871: 2314 Columbia Street | E871: Chest Springs | F871: PA | G871: 16624 | H871: 30 | I871: 15 | J871: 0 | K871: 0 | L871: wireless_unlicensed
A872: 1945059 | B872: =VLOOKUP(A872,'Subscribers Address'!A:G,6, FALSE) -> 40.566559 | C872: =VLOOKUP(A872,'Subscribers Address'!A:G,7, FALSE) -> -78.593298 | D872: 354 Watt Road | E872: Ashville | F872: PA | G872: 16613 | H872: 13 | I872: 8 | J872: 0 | K872: 0 | L872: wireless_unlicensed
A873: 2025287 | B873: =VLOOKUP(A873,'Subscribers Address'!A:G,6, FALSE) -> 40.475522 | C873: =VLOOKUP(A873,'Subscribers Address'!A:G,7, FALSE) -> -78.65533 | D873: 2714 Munster Road | E873: Ebensburg | F873: PA | G873: 15931 | H873: 45 | I873: 20 | J873: 0 | K873: 0 | L873: wireless_unlicensed
A874: 2062022 | B874: =VLOOKUP(A874,'Subscribers Address'!A:G,6, FALSE) -> 40.353888 | C874: =VLOOKUP(A874,'Subscribers Address'!A:G,7, FALSE) -> -78.726674 | D874: 622 Fairview Avenue | E874: Sidman | F874: PA | G874: 15955 | H874: 13 | I874: 8 | J874: 0 | K874: 0 | L874: wireless_unlicensed
A875: 2110786 | B875: =VLOOKUP(A875,'Subscribers Address'!A:G,6, FALSE) -> 40.528605 | C875: =VLOOKUP(A875,'Subscribers Address'!A:G,7, FALSE) -> -78.63527 | D875: 701 Eckenrode Road | E875: Loretto | F875: PA | G875: 15940 | H875: 110 | I875: 110 | J875: 0 | K875: 0 | L875: Fiber
A876: 2156476 | B876: =VLOOKUP(A876,'Subscribers Address'!A:G,6, FALSE) -> 40.561801 | C876: =VLOOKUP(A876,'Subscribers Address'!A:G,7, FALSE) -> -78.634654 | D876: 379 Krug Road | E876: Loretto | F876: PA | G876: 15940 | H876: 110 | I876: 110 | J876: 0 | K876: 0 | L876: Fiber
A877: 2175031 | B877: =VLOOKUP(A877,'Subscribers Address'!A:G,6, FALSE) -> 40.141898 | C877: =VLOOKUP(A877,'Subscribers Address'!A:G,7, FALSE) -> -78.834247 | D877: 464 Miller Run Road | E877: Hooversville | F877: PA | G877: 15936 | H877: 30 | I877: 15 | J877: 0 | K877: 0 | L877: wireless_unlicensed
A878: 2184768 | B878: =VLOOKUP(A878,'Subscribers Address'!A:G,6, FALSE) -> 40.585996 | C878: =VLOOKUP(A878,'Subscribers Address'!A:G,7, FALSE) -> -78.830765 | D878: 511 Amadei Road | E878: Ebensburg | F878: PA | G878: 15931 | H878: 30 | I878: 20 | J878: 0 | K878: 0 | L878: wireless_unlicensed
... A922: 1669847 | B922: =VLOOKUP(A922,'Subscribers Address'!A:G,6, FALSE) -> 40.623025 | C922: =VLOOKUP(A922,'Subscribers Address'!A:G,7, FALSE) -> -78.773959 | D922: 783 Buckwheat Hill Road | E922: Nicktown | F922: PA | G922: 15722 | H922: 13 | I922: 8 | J922: 0 | K922: 0 | L922: wireless_unlicensed
A923: 1669934 | B923: 40.544942 | C923: -78.594153 | D923: 195 Jefferson Street | E923: Ashville | F923: PA | G923: 16613 | H923: 13 | I923: 8 | J923: 0 | K923: 0 | L923: wireless_unlicensed
A924: 1670162 | B924: =VLOOKUP(A924,'Subscribers Address'!A:G,6, FALSE) -> 40.578484 | C924: =VLOOKUP(A924,'Subscribers Address'!A:G,7, FALSE) -> -78.689642 | D924: 192 Kane Rd | E924: Carrolltown | F924: PA | G924: 15722 | H924: 30 | I924: 15 | J924: 0 | K924: 0 | L924: wireless_unlicensed
A925: 1670428 | B925: =VLOOKUP(A925,'Subscribers Address'!A:G,6, FALSE) -> 40.515061 | C925: =VLOOKUP(A925,'Subscribers Address'!A:G,7, FALSE) -> -78.626951 | D925: 399 Columbia Street | E925: Loretto | F925: PA | G925: 15940 | H925: 30 | I925: 15 | J925: 0 | K925: 0 | L925: wireless_unlicensed
A926: 1833394 | B926: =VLOOKUP(A926,'Subscribers Address'!A:G,6, FALSE) -> 40.594566 | C926: =VLOOKUP(A926,'Subscribers Address'!A:G,7, FALSE) -> -78.846581 | D926: 159 Water Plant Road | E926: Nicktown | F926: PA | G926: 15762 | H926: 30 | I926: 15 | J926: 0 | K926: 0 | L926: wireless_unlicensed
A927: 1894711 | B927: =VLOOKUP(A927,'Subscribers Address'!A:G,6, FALSE) -> 40.469843 | C927: =VLOOKUP(A927,'Subscribers Address'!A:G,7, FALSE) -> -79.213581 | D927: 949 Campbells Mill Road | E927: Blairsville | F927: PA | G927: 15717 | H927: 57 | I927: 20 | J927: 0 | K927: 0 | L927: wireless_unlicensed
A928: 2343344 | B928: =VLOOKUP(A928,'Subscribers Address'!A:G,6, FALSE) -> 39.789222 | C928: =VLOOKUP(A928,'Subscribers Address'!A:G,7, FALSE) -> -78.921299 | D928: 145 Hunting Lane | E928: Meyersdale | F928: PA | G928: 15552 | H928: 30 | I928: 15 | J928: 0 | K928: 0 | L928: wireless_unlicensed
A929: 2345662 | B929: =VLOOKUP(A929,'Subscribers Address'!A:G,6, FALSE) -> 40.478706 | C929: =VLOOKUP(A929,'Subscribers Address'!A:G,7, FALSE) -> -78.658004 | D929: 2842 Munster Road | E929: Ebensburg | F929: PA | G929: 15931 | H929: 45 | I929: 20 | J929: 1 | K929: 0 | L929: wireless_unlicensed
A930: 1668698 | B930: =VLOOKUP(A930,'Subscribers Address'!A:G,6, FALSE) -> 40.367908 | C930: =VLOOKUP(A930,'Subscribers Address'!A:G,7, FALSE) -> -78.744986 | D930: 1290 Frankstown Road | E930: Sidman | F930: PA | G930: 15955 | H930: 13 | I930: 8 | J930: 0 | K930: 0 | L930: wireless_unlicensed
A931: 1669004 | B931: 40.576935 | C931: -78.617441 | D931: 211 SR 1008 | E931: Patton | F931: PA | G931: 16668 | H931: 220 | I931: 220 | J931: 0 | K931: 0 | L931: Fiber
A932: 1669005 | B932: =VLOOKUP(A932,'Subscribers Address'!A:G,6, FALSE) -> 40.543691 | C932: =VLOOKUP(A932,'Subscribers Address'!A:G,7, FALSE) -> -78.572824 | D932: 262 Kid Long Rd | E932: Gallitizin | F932: PA | G932: 16641 | H932: 110 | I932: 110 | J932: 0 | K932: 0 | L932: Fiber
A933: 1669091 | B933: =VLOOKUP(A933,'Subscribers Address'!A:G,6, FALSE) -> 40.55487 | C933: =VLOOKUP(A933,'Subscribers Address'!A:G,7, FALSE) -> -78.891042 | D933: 1595 Historical Road | E933: Strongstown | F933: PA | G933: 15957 | H933: 30 | I933: 15 | J933: 0 | K933: 0 | L933: wireless_unlicensed
A934: 1669304 | B934: =VLOOKUP(A934,'Subscribers Address'!A:G,6, FALSE) -> 40.491937 | C934: =VLOOKUP(A934,'Subscribers Address'!A:G,7, FALSE) -> -78.625101 | D934: 435 Itle Rd | E934: Loretto | F934: PA | G934: 15940 | H934: 13 | I934: 8 | J934: 0 | K934: 0 | L934: wireless_unlicensed
A935: 1669316 | B935: =VLOOKUP(A935,'Subscribers Address'!A:G,6, FALSE) -> 40.226116 | C935: =VLOOKUP(A935,'Subscribers Address'!A:G,7, FALSE) -> -78.654129 | D935: 747 Mountain Road | E935: Alum Bank | F935: PA | G935: 15521 | H935: 57 | I935: 20 | J935: 0 | K935: 0 | L935: wireless_unlicensed
A936: 1669937 | B936: =VLOOKUP(A936,'Subscribers Address'!A:G,6, FALSE) -> 40.480111 | C936: =VLOOKUP(A936,'Subscribers Address'!A:G,7, FALSE) -> -78.662452 | D936: 151 Harvey Ln | E936: Ebensburg | F936: PA | G936: 15931 | H936: 30 | I936: 15 | J936: 0 | K936: 0 | L936: wireless_gaa
A937: 1670388 | B937: =VLOOKUP(A937,'Subscribers Address'!A:G,6, FALSE) -> 40.531925 | C937: =VLOOKUP(A937,'Subscribers Address'!A:G,7, FALSE) -> -78.581545 | D937: 605 Back Rd. | E937: Gallitzin | F937: PA | G937: 16641 | H937: 110 | I937: 110 | J937: 0 | K937: 0 | L937: Fiber
...

Sheet Customer speedlimit
A1: Customer ID | B1: Package Name | C1: Service Name | D1: Down Speed | E1: Up Speed
A2: 1668594 | B2: 10Mb Residential | C2: Wireless | D2: 13mbps | E2: 8mbps
A3: 1668598 | B3: 10Mb Residential | C3: Wireless | D3: 30mbps | E3: 12mbps
A4: 1668603 | B4: 25Mb Residential | C4: Wireless | D4: 30mbps | E4: 15mbps
A5: 1668604 | B5: 25Mb Residential | C5: Wireless | D5: 30mbps | E5: 15mbps
A6: 1668608 | B6: 10Mb Residential | C6: Wireless | D6: 13mbps | E6: 8mbps
A7: 1668611 | B7: 25Mb Residential | C7: Wireless | D7: 30mbps | E7: 15mbps
A8: 1668615 | B8: 25Mb Residential | C8: Wireless | D8: 30mbps | E8: 15mbps
A9: 1668618 | B9: 10Mb Residential | C9: Wireless | D9: 13mbps | E9: 8mbps
A10: 1668625 | B10: 50Mb Residential | C10: Wireless | D10: 57mbps | E10: 20mbps
A11: 1668626 | B11: 40Mb Residential | C11: Wireless | D11: 45mbps | E11: 20mbps
A12: 1668641 | B12: 25Mb Residential | C12: Wireless | D12: 30mbps | E12: 15mbps
A13: 1668643 | B13: 25Mb Residential | C13: Wireless | D13: 30mbps | E13: 15mbps
... A1924: 2567810 | B1924: 50Mb Residential | C1924: Wireless | D1924: 57mbps | E1924: 20mbps
A1926: Count
A1927: 1923

Sheet Package Information
A1: Name | B1: Description | C1: Services | D1: Includes | E1: Internet Service Label | F1: Package Type | G1: Internet Service Download Speed | H1: Internet Service Upload Speed
A2: 1 Gb Fiber Business | B2: 1 Gb Fiber Business | C2: 1Internet | D2: 1000 x 1000 | E2: Internet | F2: Business | G2: 1000mbps | H2: 1000mbps
A3: 100Mbps Fiber Business | B3: 100Mbps Fiber Business | C3: 1InternetService | D3: 100 x 100 | E3: InternetService | F3: Business | G3: 100mbps | H3: 100mbps
A4: 10Mb Business | C4: 110MbBusinessInternetService | E4: 10MbBusinessInternetService | F4: Business | G4: 13mbps | H4: 8mbps
A5: 200Mbps Fiber Business | B5: 200Mbps Fiber Business | C5: 1InternetService | D5: 200 x 200 | E5: InternetService | F5: Business | G5: 200mbps | H5: 200mbps
A6: 25Mb Business | C6: 125MbBusinessInternetService | E6: 25MbBusinessInternetService | F6: Business | G6: 30mbps | H6: 15mbps
A7: 400Mbps Fiber Business | B7: 400Mbps Fiber Business | C7: 1InternetService | D7: 400 x 400 | E7: InternetService | F7: Business | G7: 400mbps | H7: 400mbps
A8: 50Mb Metro Business | C8: 1Internet | E8: Internet | F8: Business | G8: 50mbps | H8: 10mbps
A9: 75Mb Business Dedicated Internet with Tower Support | C9: 1Internet | E9: Internet | F9: Business | G9: 75mbps | H9: 50mbps
A10: 75Mbps Metro Business | B10: 75Mbps Metro Business | C10: 1Internet | E10: Internet | F10: Business | G10: 75mbps | H10: 10mbps
A11: Tower Rent | C11: 1TowerRent | F11: Business
A12: 1 GB Fiber Residential | B12: 1 Gb Fiber Residential | C12: 1InternetService | D12: 1000 x 1000 | E12: InternetService | F12: Residential | G12: 1000mbps | H12: 1000mbps
A13: 1 GB Wave | B13: 1 GB Wave | C13: 1Internet | D13: 1 GB Wave | E13: Internet | F13: Residential | G13: 1000mbps | H13: 1000mbps
A14: 1 GB Wave Business | B14: 1 GB Wave Business | C14: 1Internet | D14: 1 GB Wave Business | E14: Internet | F14: Residential | G14: 1000mbps | H14: 1000mbps
A15: 100 Mb Fiber Internet | B15: 100 Mb Fiber Internet | C15: 1Internet | D15: 100 Mb Fiber Internet | E15: Internet | F15: Residential | G15: 110mbps | H15: 110mbps
A16: 100 Mb Fiber Internet $64.95 | B16: 100 Mb Fiber Internet $64.95 | C16: 1Internet | D16: 100 Mb Fiber Internet $64.95 | E16: Internet | F16: Residential | G16: 110mbps | H16: 110mbps
A17: 100 MB Wave | B17: 100 MB Wave | C17: 1Internet | D17: 100 MB Wave | E17: Internet | F17: Residential | G17: 110mbps | H17: 110mbps
A18: 100 MB Wave Business | B18: 100 MB Wave Business | C18: 1Internet | D18: 100 MB Wave Business | E18: Internet | F18: Residential | G18: 110mbps | H18: 110mbps
A19: 100Mb Fiber Internet* | B19: 100Mb Fiber Internet* | C19: 1Internet | D19: 100Mb Fiber Internet* | E19: Internet | F19: Residential | G19: 110mbps | H19: 20mbps
A20: 100Mb Metro Residential | C20: 1Internet | E20: Internet | F20: Residential | G20: 100mbps | H20: 20mbps
A21: 10Mb Residential | C21: 1Internet | E21: Internet | F21: Residential | G21: 13mbps | H21: 8mbps
A22: 15 Mbps Fiber Internet | B22: 15 Mbps Fiber Internet | C22: 1Internet | E22: Internet | F22: Residential | G22: 15mbps | H22: 20mbps
A23: 200 MB Wave | B23: 200 MB Wave | C23: 1Internet | D23: 200 MB Wave | E23: Internet | F23: Residential | G23: 220mbps | H23: 220mbps
A24: 200 Mb Wave Business | B24: 200 Mb Wave Business | C24: 1Internet | D24: 200 Mb Wave Business | E24: Internet | F24: Residential | G24: 220mbps | H24: 220mbps
A25: 200 Mbps Fiber Internet | B25: 200 Mbps Fiber Internet | C25: 1Internet | D25: 200 Mbps Fiber Internet | E25: Internet | F25: Residential | G25: 220mbps | H25: 220mbps
A26: 200Mb Fiber Internet* | B26: 200Mb Fiber Internet* | C26: 1Internet | D26: 200Mb Fiber Internet* | E26: Internet | F26: Residential | G26: 220mbps | H26: 40mbps
A27: 25 Mbps Fiber internet | B27: 25 Mbps Fiber Internet | C27: 1Internet | E27: Internet | F27: Residential
A28: 25 Mbps Metro Business | B28: 25 Mbps Metro Business | C28: 1Internet | E28: Internet | F28: Residential
A29: 25Mb Metro Residential | C29: 1Internet | E29: Internet | F29: Residential | G29: 25mbps | H29: 15mbps
A30: 25Mb Residential | B30: 6Mbps Internet | C30: 125MbResidentialInternetService | D30: 6Mbps Internet | E30: 25MbResidentialInternetService | F30: Residential | G30: 30mbps | H30: 15mbps
A31: 30 Mbps- Fabin | C31: 1Internet | D31: Internet Service | E31: Internet | F31: Residential
A32: 300 Mb WAN Transport | B32: 300 Mb WAN Transport | C32: 1Internet | D32: 300 Mb WAN Transport | E32: Internet | F32: Residential | G32: 350mbps | H32: 25mbps
A33: 400 MB Wave | B33: 400 MB Wave | C33: 1Internet | D33: 400 MB Wave | E33: Internet | F33: Residential | G33: 440mbps | H33: 440mbps
A34: 400 MB Wave Business | B34: 400 MB Wave Business | C34: 1Internet | D34: 400 MB Wave Business | E34: Internet | F34: Residential | G34: 440mbps | H34: 440mbps
A35: 400 Mbps Fiber Internet | B35: 400 Mbps Fiber Internet | C35: 1Internet | D35: 400 Mbps Fiber Internet | E35: Internet | F35: Residential | G35: 440mbps | H35: 440mbps
A36: 40Mb Business | C36: 1Internet | E36: Internet | F36: Residential | G36: 40mbps | H36: 10mbps
A37: 40Mb Business | C37: 140MbBusinessInternetService | E37: 40MbBusinessInternetService | F37: Residential | G37: 45mbps | H37: 20mbps
A38: 40Mb Residential | C38: 1Internet | E38: Internet | F38: Residential | G38: 45mbps | H38: 20mbps
A39: 500 MB Wave | B39: 500 MB Wave | C39: 1Internet | D39: 500 MB Wave | E39: Internet | F39: Residential | G39: 550mbps | H39: 550mbps
A40: 50Mb Business | C40: 150MbBusinessInternetService | E40: 50MbBusinessInternetService | F40: Residential | G40: 55mbps | H40: 25mbps
A41: 50Mb Dedicated Wireless | C41: 1Internet | E41: Internet | F41: Residential
A42: 50Mb Fiber Internet $64.95* | B42: 50Mb Fiber Internet $64.95* | C42: 1Internet | D42: 50Mb Fiber Internet $64.95* | E42: Internet | F42: Residential | G42: 55mbps | H42: 10mbps
A43: 50Mb Fiber Internet* | B43: 50Mb Fiber Internet* | C43: 1Internet | D43: 50Mb Fiber Internet* | E43: Internet | F43: Residential | G43: 55mbps | H43: 25mbps
A44: 50Mb Metro Residential | C44: 1Internet | E44: Internet | F44: Residential | G44: 50mbps | H44: 20mbps
A45: 50Mb Residential | C45: 1Internet | E45: Internet | F45: Residential | G45: 57mbps | H45: 20mbps
A46: 75Mb Metro Residential | C46: 1Internet | E46: Internet | F46: Residential | G46: 75mbps | H46: 20mbps
A47: Audience Mesh System | B47: Mesh WiFi Extender | C47: 1AudienceMeshSystem | F47: Residential
A48: Chickaree Residential | C48: 1Internet | E48: Internet | F48: Residential | G48: 15mbps | H48: 3mbps
A49: Custom Internet Service | C49: 1Internet | E49: Internet | F49: Residential | G49: 100mbps | H49: 25mbps
A50: Internet Service | C50: 1Internet | E50: Internet | F50: Residential | G50: 100mbps | H50: 25mbps
A51: Managed WiFi | C51: 1ManagedWiFi | F51: Residential
A52: Quick Pay | C52: 1Custom | F52: Residential
A53: Service Installation | C53: 1Labor | F53: Residential
A54: VoIP Fax Only | C54: 1OtherService | F54: Residential
A55: VoIP Taxes and Fees Custom | C55: 1VoIPTaxes&Fees | F55: Residential
A56: VoIP Taxes and Fees ISP | B56: Gross Receipts Tax 1.27 Federal Telecommunications Relay Services Fund (Non-IPCTS) 0. VoIP 911 Surcharge 1.95 State Sales Tax 1.60 Federal Telecommunications Relay Services Fund (IPCTS) 0.52 FCC Cost Recovery Fee 0.1 Federal Universal Service Fund 4.85 ITXBB - TOTAL 10.34 | C56: 1VoIPTaxes&Fees | F56: Residential
A57: VoIP Taxes and Fees Non-ISP | B57: FCC Cost Recovery Fee 0.1 Federal Telecommunications Relay Services Fund (Non-IPCTS) 0.24 State Sales Tax 1.91 VoIP 911 Surcharge 1.65 Federal Universal Service Fund 4.82 Federal Telecommunications Relay Services Fund (IPCTS) 0.2 Gross Receipts Tax 1.52 ITXBB - TOTAL 10.42 | C57: 1VoIPTaxes&Fees | F57: Residential
A58: VoIP Unlimited | C58: 1UnlimitedVoIP | F58: Residential
A59: VoIP Unlimited ISP | C59: 1UnlimitedVoIP | F59: Residential

Sheet Subscribers Address
A1: Customer ID | B1: Address 1 | C1: City | D1: State | E1: Zip | F1: Latitude | G1: Longitude
A2: 1668592 | B2: 181 Japp Rd | C2: Summerhill | D2: PA | E2: 159580000 | F2: 40.37813 | G2: -78.760576
A3: 1668593 | B3: 126 Evergreen Road | C3: Wilmore | D3: PA | E3: 159620000 | F3: 40.389659 | G3: -78.719762
A4: 1668594 | B4: 503 Blue Road | C4: Salix | D4: PA | E4: 159520000 | F4: 40.310355 | G4: -78.786767
A5: 1668595 | B5: Cost Center 37316 | C5: Carmel | D5: IN | E5: 46082-1934 | F5: 39.978371 | G5: -86.118043
A6: 1668596 | B6: 445 Schoolhouse Road | C6: Johnstown | D6: PA | E6: 159040000 | F6: 40.271261 | G6: -78.830384
A7: 1668597 | B7: 3135 New Germany Road | C7: Ebensburg | D7: PA | E7: 159310000 | F7: 40.463305 | G7: -78.751252
A8: 1668598 | B8: PO Box 42 | C8: Cresson | D8: PA | E8: 166300000 | F8: 40.459794 | G8: -78.591684
A9: 1668599 | B9: 142 Almary Lane | C9: Dysart | D9: PA | E9: 166360000 | F9: 40.596734 | G9: -78.516962
A10: 1668600 | B10: 1405 Menoher Blvd | C10: Johnstown | D10: PA | E10: 159050000 | F10: 40.31572 | G10: -78.950773
A11: 1668601 | B11: 116 Pioneer Lake Trail | C11: Cherry Tree | D11: PA | E11: 157240000 | F11: 40.73568 | G11: -78.859282
A12: 1668602 | B12: 1625 Liberty Street | C12: Ashville | D12: PA | E12: 166130000 | F12: 40.559265 | G12: -78.547563
A13: 1668603 | B13: 147 Adams Ln | C13: Dysart | D13: PA | E13: 166360000 | F13: 40.606096 | G13: -78.575413
A14: 1668604 | B14: 209 Adams Ln | C14: Dysart | D14: PA | E14: 16636 | F14: 40.605445 | G14: -78.578867
A15: 1668605 | B15: 300 Laurel Avenie | C15: Cresson | D15: PA | E15: 166300000 | F15: 40.461584 | G15: -78.58813
A16: 1668607 | B16: 1749 Lyter Drive | C16: Johnstown | D16: PA | E16: 159050000 | F16: 40.321498 | G16: -78.956408
A17: 1668608 | B17: 417 VFW Road | C17: Carrolltown | D17: PA | E17: 157220271 | F17: 40.566477 | G17: -78.692855
... A90: 1668684 | B90: 570 Benshoff Road | C90: Summerhill | D90: PA | E90: 159580000 | F90: 40.416176 | G90: -78.775087
A91: 1668685 | B91: 138 Elm Street | C91: Fallentimber | D91: PA | E91: 16639-6208 | F91: 40.650398 | G91: -78.51119
A92: 1668686 | B92: 521 Summit St | C92: Gallitzin | D92: PA | E92: 166410000 | F92: 40.486342 | G92: -78.548177
A93: 1668687 | B93: 5239 Ridge Road | C93: Westover | D93: PA | E93: 16692 | F93: 40.778443 | G93: -78.726436
A94: 1668688 | B94: 1186 Jefferson St | C94: Loretto | D94: PA | E94: 159400000 | F94: 40.575891 | G94: -78.60844
A95: 1668689 | B95: 534 Berkey Road | C95: Bo | D95: PA | E95: 155310000 | F95: 32.83921 | G95: -97.115306
A96: 1668690 | B96: 905 Wess Rd | C96: Mineral Point | D96: PA | E96: 159420000 | F96: 40.406037 | G96: -78.780357
A97: 1668691 | B97: 156 Shimko Ln | C97: Nicktown | D97: PA | E97: 157620000 | F97: 40.612867 | G97: -78.811332
A98: 1668692 | B98: 217 Miller Rd | C98: Ebensburg | D98: PA | E98: 159310000 | F98: 40.559068 | G98: -78.735057
A99: 1668693 | B99: 172 Poole Lane | C99: Ebensburg | D99: PA | E99: 159310000 | F99: 40.575453 | G99: -78.689442
A100: 1668694 | B100: 605 Church Hill | C100: Portage | D100: PA | E100: 159460000 | F100: 40.397188 | G100: -78.698946
A101: 1668695 | B101: 594 George Lane | C101: Seward | D101: PA | E101: 159540000 | F101: 40.444795 | G101: -78.994864
A102: 1668696 | B102: 889 Wess Rd | C102: Mineral Point | D102: PA | E102: 159420000 | F102: 40.405277 | G102: -78.780387
A103: 1668697 | B103: 841 Munster Road | C103: Portage | D103: PA | E103: 159460000 | F103: 40.415985 | G103: -78.677398
... A191: 1668786 | B191: 1501 Swigle Mountain Rd | C191: Mineral Point | D191: PA | E191: 15942 | F191: 40.407696 | G191: -78.805513
A192: 1668787 | B192: 873 Wess Road | C192: Mineral Point | D192: PA | E192: 15942-5231 | F192: 40.404735 | G192: -78.780455
A193: 1668788 | B193: 5596 Camerons Road | C193: Homer City | D193: PA | E193: 157480000 | F193: 40.530572 | G193: -78.942452
A194: 1668789 | B194: 117 Alba Drive | C194: Lilly | D194: PA | E194: 159380000 | F194: 40.453185 | G194: -78.588138
A195: 1668791 | B195: 712 Gates Road | C195: Fallentimber | D195: PA | E195: 16639 | F195: 40.639523 | G195: -78.512197
A196: 1668792 | B196: Lot 106 | C196: Fallentimber | D196: PA | E196: 166390000 | F196: 40.686731 | G196: -78.499187
A197: 1668793 | B197: 3082 Colonel Drake Highway | C197: Chest Springs | D197: PA | E197: 166240000 | F197: 40.581348 | G197: -78.606862
A198: 1668794 | B198: 2798 Menoher Blvd. | C198: Johnstown | D198: PA | E198: 15905 | F198: 40.308453 | G198: -78.985596
A199: 1668795 | B199: 804 Thompson Road | C199: Blairsville | D199: PA | E199: 157170000 | F199: 40.486218 | G199: -79.240279
A200: 1668796 | B200: 94 Zenith Road | C200: Cherry Tree | D200: PA | E200: 157240000 | F200: 40.686597 | G200: -78.841611
A201: 1668797 | B201: 348 Beck Road | C201: Loretto | D201: PA | E201: 159400000 | F201: 40.551222 | G201: -78.656775
A202: 1668798 | B202: 1578 Columbia Street | C202: Loretto | D202: PA | E202: 159400000 | F202: 40.556534 | G202: -78.622784
A203: 1668799 | B203: 1589 Columbia Street | C203: Loretto | D203: PA | E203: 159400000 | F203: 40.55739 | G203: -78.621911
A204: 1668800 | B204: 525 Gates Hill Rd | C204: Summerhill | D204: PA | E204: 159580000 | F204: 40.395922 | G204: -78.736613
... A208: 1668804 | B208: 257 Timothy Dr | C208: Loretto | D208: PA | E208: 159400000 | F208: 40.468432 | G208: -78.628328
A209: 1668805 | B209: 4254 Tipperary Rd | C209: Northern Cambria | D209: PA | E209: 15714-9345 | F209: 40.625318 | G209: -78.861897
A210: 1668806 | B210: 177 Hillside Dr | C210: Ashville | D210: PA | E210: 166130000 | F210: 40.548557 | G210: -78.522788
A211: 1668807 | B211: 2149 Dutch Road | C211: Loretto | D211: PA | E211: 15940 | F211: 40.555964 | G211: -78.645481
A212: 1668808 | B212: 1312 S. Blair St. | C212: Portage | D212: PA | E212: 159460000 | F212: 40.376039 | G212: -78.67676
A213: 1668809 | B213: 161 McConnell | C213: Lo | D213: PA | E213: 159400000 | F213: 41.203322 | G213: -77.194525
A214: 1668810 | B214: 403 Highway South | C214: Homer City | D214: PA | E214: 157480000 | F214: 40.458735 | G214: -79.0109
A215: 1668811 | B215: 114 Main St | C215: Fallentimber | D215: PA | E215: 166930000 | F215: 40.686731 | G215: -78.499187
A216: 1668812 | B216: 184 Kline Rd | C216: Carrolltown | D216: PA | E216: 157220000 | F216: 40.615306 | G216: -78.7092
A217: 1668813 | B217: 131 Slate Ln | C217: Ebensburg | D217: PA | E217: 159310000 | F217: 40.562602 | G217: -78.677
A218: 1668814 | B218: 5037 Route 403 Hwy South | C218: Homer City | D218: PA | E218: 157480000 | F218: 40.638503 | G218: -78.942307
A219: 1668815 | B219: 921 Gates Hill Rd. | C219: Summerhill | D219: PA | E219: 159580000 | F219: 40.40626 | G219: -78.747504
A220: 1668816 | B220: 112 Cabin Lane | C220: Loretto | D220: PA | E220: 15940 | F220: 40.551198 | G220: -78.674664
A221: 1668817 | B221: 147 apple lane | C221: Loretto | D221: PA | E221: 159400000 | F221: 40.503126 | G221: -78.630296
... A298: 1668895 | B298: 172 Noel Lane | C298: Gallitzin | D298: PA | E298: 166410000 | F298: 40.54109 | G298: -78.570996
A299: 1668896 | B299: 635 Hidden Valley Rd | C299: Boswell | D299: PA | E299: 15531-1714 | F299: 40.2494 | G299: -79.005454
A300: 1668897 | B300: 210 Brookbank Drive | C300: Summerhill | D300: PA | E300: 159580000 | F300: 40.355688 | G300: -78.689646
A301: 1668898 | B301: 306 Gates Hill Road | C301: Summerhill | D301: PA | E301: 159580000 | F301: 40.390531 | G301: -78.727027
A302: 1668899 | B302: 325 Black Road | C302: Sidman | D302: PA | E302: 159550000 | F302: 40.347757 | G302: -78.741376
A303: 1668900 | B303: 1431 Swigle Mountain Rd. | C303: Mineral Point | D303: PA | E303: 159420000 | F303: 40.403493 | G303: -78.80114
A304: 1668901 | B304: 2155 Dutch Rd | C304: Loretto | D304: PA | E304: 159400000 | F304: 40.555401 | G304: -78.645422
A305: 1668902 | B305: 169 Cummings Lane | C305: Summerhill | D305: PA | E305: 159580000 | F305: 40.396822 | G305: -78.748645
A306: 1668903 | B306: 1091 Lemon Drop Road | C306: Ebensburg | D306: PA | E306: 15931 | F306: 40.548829 | G306: -78.679015
A307: 1668904 | B307: 1237 St Augustine Rd | C307: Dysart | D307: PA | E307: 16636 | F307: 40.62097 | G307: -78.558969
A308: 1668905 | B308: 724 Cunningham Rd | C308: Ebensburg | D308: PA | E308: 159310000 | F308: 40.540379 | G308: -78.682303
A309: 1668906 | B309: 698 Cunningham Road | C309: Ebensburg | D309: PA | E309: 159310000 | F309: 40.543711 | G309: -78.682306
A310: 1668907 | B310: 1057 Lemon Drop Rd | C310: Ebensburg | D310: PA | E310: 159310000 | F310: 40.550519 | G310: -78.681
A311: 1668908 | B311: 2400 Veterans Memorial Hwy | C311: Altoona | D311: PA | E311: 166010000 | F311: 40.497946 | G311: -78.485295
A312: 1668909 | B312: 218 Pennsylvania Ave West | C312: Warren | D312: PA | E312: 16365-2413 | F312: 41.844011 | G312: -79.145682
A313: 1668910 | B313: 151 Oakbrook Lane | C313: Johnstown | D313: PA | E313: 159046807 | F313: 40.299821 | G313: -78.800026
A314: 1668912 | B314: 339 Varner Rd | C314: Mineral Point | D314: PA | E314: 159420000 | F314: 40.38941 | G314: -78.80033
A315: 1668913 | B315: 538 Harshberger Road | C315: Johnstown | D315: PA | E315: 159050000 | F315: 40.305067 | G315: -78.939936
A316: 1668914 | B316: 150 Speicher Ln | C316: Boswell | D316: PA | E316: 155310000 | F316: 40.253565 | G316: -79.010099
A317: 1668915 | B317: 132 Colver Road | C317: Ebensburg | D317: PA | E317: 159310000 | F317: 40.49695 | G317: -78.736406
A318: 1668916 | B318: 972 Jefferson Street | C318: Chest Springs | D318: PA | E318: 166240000 | F318: 40.568255 | G318: -78.605413
A319: 1668917 | B319: PO Box 513 | C319: Colver | D319: PA | E319: 159270000 | F319: 40.542571 | G319: -78.789812
A320: 1668918 | B320: 1134 Schoolhouse Dr | C320: Dysart | D320: PA | E320: 166360000 | F320: 40.59277 | G320: -78.566711
A321: 1668919 | B321: 170 Varner Road | C321: Mineral Point | D321: PA | E321: 159420000 | F321: 40.386447 | G321: -78.805957
A322: 1668920 | B322: 493 Beck Road | C322: Loretto | D322: PA | E322: 159400000 | F322: 40.545579 | G322: -78.65656
A323: 1668921 | B323: 1735 Frankstown Rd | C323: Summermill | D323: PA | E323: 159580000 | F323: 40.36134 | G323: -78.727006
A324: 1668922 | B324: 107 Beck Rd | C324: Loretto | D324: PA | E324: 159400000 | F324: 40.553386 | G324: -78.645344
... A432: 1669033 | B432: 1554 Swigle Mountain Rd | C432: Mineral Point | D432: PA | E432: 159420000 | F432: 40.405043 | G432: -78.805465
A433: 1669034 | B433: Panda-3015 Care of AT and T | C433: Carol Stream | D433: IL | E433: 60197-5003 | F433: 41.912529 | G433: -88.134793
A434: 1669035 | B434: 712 2nd Street | C434: Cresson | D434: PA | E434: 166300000 | F434: 40.462921 | G434: -78.589726
A435: 1669036 | B435: 883 N Julian Street | C435: Ebensburg | D435: PA | E435: 159310000 | F435: 40.4928 | G435: -78.726959
A436: 1669038 | B436: 404 Columbia Street | C436: Loretto | D436: PA | E436: 15940 | F436: 40.520421 | G436: -78.63646
A437: 1669039 | B437: 2635 Brick Rd | C437: Ebensburg | D437: PA | E437: 159310000 | F437: 40.570044 | G437: -78.685535
A438: 1669040 | B438: 653 Feighner Rd | C438: Carrolltown | D438: PA | E438: 157220000 | F438: 40.590372 | G438: -78.673864
A439: 1669041 | B439: 312 Noll Rd | C439: Loretto | D439: PA | E439: 159400000 | F439: 40.517 | G439: -78.616954
A440: 1669042 | B440: 290 Maple Ln | C440: Loretto | D440: PA | E440: 159400000 | F440: 40.541387 | G440: -78.623452
A441: 1669043 | B441: 473 Brawley Rd | C441: Carrolltown | D441: PA | E441: 157220000 | F441: 40.577388 | G441: -78.755364
A442: 1669044 | B442: 220 Maple Lane | C442: Loretto | D442: PA | E442: 159400000 | F442: 40.543082 | G442: -78.620822
A443: 1669045 | B443: 2335 Brick Rd | C443: Ebenburg | D443: PA | E443: 159310000 | F443: 40.566526 | G443: -78.676719
A444: 1669046 | B444: 157 Baker Lane | C444: Loretto | D444: PA | E444: 159400000 | F444: 40.549439 | G444: -78.652841
A445: 1669047 | B445: 184 Baker Lane | C445: Loretto | D445: PA | E445: 15940 | F445: 40.550152 | G445: -78.651663
...
